setup.py
distributions/Binomialdistribution.py
distributions/Gaussiandistribution.py
distributions/Generaldistribution.py
distributions/__init__.py
jr_distributions.egg-info/PKG-INFO
jr_distributions.egg-info/SOURCES.txt
jr_distributions.egg-info/dependency_links.txt
jr_distributions.egg-info/not-zip-safe
jr_distributions.egg-info/top_level.txt