Metadata-Version: 1.0
Name: jr-distributions
Version: 1.0
Summary: JR Gaussian distributions
Home-page: UNKNOWN
Author: Joel Ruetas
Author-email: contact@joelruetas.com
License: UNKNOWN
Platform: UNKNOWN
